Metadata-Version: 2.1
Name: ABTS
Version: 0.0.3
Summary: algorithm for Agent Based Travel Scheduler
Home-page: https://github.com/MG-Choi/ABTS
Author: MoongiChoi
Author-email: u1316663@utah.edu
License: UNKNOWN
Platform: UNKNOWN
Requires-Dist: tqdm
Requires-Dist: numpy
Requires-Dist: pandas
Requires-Dist: shapely (>=2.0.2)
Requires-Dist: pyproj (>=3.3.0)
Requires-Dist: geopandas (>=0.14.0)
Requires-Dist: networkx (>=3.2.1)
Requires-Dist: osmnx (>=1.7.1)
Requires-Dist: geopy (>=2.2.0)
